deepl_haystack/__init__.py
deepl_haystack/components.py
deepl_haystack-0.3.0.dist-info/METADATA
deepl_haystack-0.3.0.dist-info/WHEEL
deepl_haystack-0.3.0.dist-info/licenses/LICENSE
deepl_haystack-0.3.0.dist-info/RECORD
