Metadata-Version: 2.4
Name: deepl-haystack
Version: 0.3.0
Summary: Haystack integration with DeepL translation services provider.
Project-URL: Homepage, https://github.com/dribia/deepl-haystack
Project-URL: Repository, https://github.com/dribia/deepl-haystack
Project-URL: Bug Tracker, https://github.com/dribia/deepl-haystack/issues
Author-email: Albert Iribarne <iribarne@dribia.com>
Maintainer-email: Dribia Data Research <code@dribia.com>
License-Expression: MIT
License-File: LICENSE
Keywords: deepl,haystack,nlp,translation
Classifier: Development Status :: 4 - Beta
Classifier: Intended Audience :: Science/Research
Classifier: License :: OSI Approved :: MIT License
Classifier: Operating System :: OS Independent
Classifier: Programming Language :: Python :: 3 :: Only
Classifier: Programming Language :: Python :: 3.9
Classifier: Programming Language :: Python :: 3.10
Classifier: Programming Language :: Python :: 3.11
Classifier: Programming Language :: Python :: 3.12
Classifier: Programming Language :: Python :: 3.13
Classifier: Topic :: Scientific/Engineering :: Artificial Intelligence
Requires-Python: <3.14,>=3.9
Requires-Dist: deepl<2,>=1.19.1
Requires-Dist: haystack-ai<3,>=2.0.0
Requires-Dist: pytest-dotenv<0.6,>=0.5.2
Requires-Dist: pytest<9,>=8.4.1
